{
  "resourceType": "StructureDefinition",
  "id": "frequency",
  "url": "http://hl7.org/fhir/dbcg/core/ImplementationGuide/core/StructureDefinition/frequency",
  "name": "Frequency",
  "title": "Frequency",
  "status": "draft",
  "experimental": false,
  "fhirVersion": "4.0.0",
  "kind": "resource",
  "abstract": false,
  "type": "MedicationDispense",
  "baseDefinition": "http://hl7.org/fhir/StructureDefinition/MedicationDispense",
  "derivation": "constraint",
  "differential": {
    "element": [
      {
        "id": "MedicationDispense",
        "path": "MedicationDispense",
        "mustSupport": false
      },
      {
        "id": "MedicationDispense.dosageInstruction.timing.repeat",
        "path": "MedicationDispense.dosageInstruction.timing.repeat",
        "min": 0,
        "max": "1",
        "mustSupport": true
      }
    ]
  }
}